camtools/__init__.py
camtools/artifact.py
camtools/camera.py
camtools/colmap.py
camtools/colormap.py
camtools/convert.py
camtools/geometry.py
camtools/image.py
camtools/io.py
camtools/metric.py
camtools/normalize.py
camtools/project.py
camtools/raycast.py
camtools/render.py
camtools/sanity.py
camtools/solver.py
camtools/transform.py
camtools/util.py
camtools/tools/__init__.py
camtools/tools/cli.py
camtools/tools/compress_images.py
camtools/tools/crop_boarders.py
camtools/tools/draw_bboxes.py
camtools-0.1.7.dist-info/LICENSE
camtools-0.1.7.dist-info/METADATA
camtools-0.1.7.dist-info/WHEEL
camtools-0.1.7.dist-info/entry_points.txt
camtools-0.1.7.dist-info/top_level.txt
camtools-0.1.7.dist-info/RECORD
