Metadata-Version: 2.2
Name: camtools
Version: 0.1.7
Summary: CamTools: Camera Tools for Computer Vision.
Author: Yixing Lao
License: MIT
Project-URL: Homepage, https://github.com/yxlao/camtools
Classifier: Programming Language :: Python :: 3
Requires-Python: >=3.8.0
License-File: LICENSE
Requires-Dist: numpy>=1.15.0
Requires-Dist: open3d>=0.16.0
Requires-Dist: opencv-python>=4.5.1.48
Requires-Dist: matplotlib>=3.3.4
Requires-Dist: scikit-image>=0.16.2
Requires-Dist: tqdm>=4.60.0
Requires-Dist: jaxtyping>=0.2.12
Provides-Extra: dev
Requires-Dist: black>=22.1.0; extra == "dev"
Requires-Dist: pytest>=6.2.2; extra == "dev"
Requires-Dist: pytest-benchmark>=4.0.0; extra == "dev"
Requires-Dist: ipdb; extra == "dev"
Provides-Extra: docs
Requires-Dist: sphinx; extra == "docs"
Requires-Dist: sphinx-rtd-theme; extra == "docs"
Requires-Dist: myst-parser; extra == "docs"
Requires-Dist: furo; extra == "docs"
Requires-Dist: tomli; extra == "docs"
Provides-Extra: torch
Requires-Dist: torch>=1.8.0; extra == "torch"
Requires-Dist: lpips>=0.1.4; extra == "torch"
